LICENSE
MANIFEST.in
README.rst
setup.py
apegears/__init__.py
apegears/func_argparse.py
apegears/iofile.py
apegears/lo99ing.py
apegears/misc.py
apegears/parser.py
apegears/spec.py
apegears/types.py
apegears/version.py
apegears.egg-info/PKG-INFO
apegears.egg-info/SOURCES.txt
apegears.egg-info/dependency_links.txt
apegears.egg-info/top_level.txt