Metadata-Version: 1.1
Name: apegears
Version: 0.2.2
Summary: An improved ArgumentParser, fully compatible with argparse.
Home-page: https://github.com/shx2/apegears
Author: shx2
Author-email: shx222@gmail.com
License: MIT
Keywords: CLI argparse ArgumentParser optparse func_argparse
Platform: POSIX
Platform: Windows
Classifier: Programming Language :: Python :: 3
Classifier: Development Status :: 3 - Alpha
Classifier: Intended Audience :: Developers
Classifier: Topic :: Software Development
Classifier: License :: OSI Approved :: MIT License
Classifier: Operating System :: POSIX
Classifier: Operating System :: Microsoft :: Windows
